edc_navbar/__init__.py
edc_navbar/apps.py
edc_navbar/auth_objects.py
edc_navbar/auths.py
edc_navbar/exceptions.py
edc_navbar/get_default_navbar.py
edc_navbar/models.py
edc_navbar/navbar.py
edc_navbar/navbar_item.py
edc_navbar/navbars.py
edc_navbar/site_navbars.py
edc_navbar/system_checks.py
edc_navbar/urls.py
edc_navbar/utils.py
edc_navbar/view_mixin.py
edc_navbar/wsgi.py
edc_navbar/migrations/0001_initial.py
edc_navbar/migrations/0002_auto_20210423_1451.py
edc_navbar/migrations/0003_alter_navbar_options.py
edc_navbar/migrations/0004_auto_20220825_0451.py
edc_navbar/migrations/0005_auto_20220910_0210.py
edc_navbar/migrations/0006_alter_edcpermissions_device_created_and_more.py
edc_navbar/migrations/0007_alter_edcpermissions_options_and_more.py
edc_navbar/migrations/__init__.py
edc_navbar/templates/edc_navbar/edc_navbar.html
edc_navbar/templates/edc_navbar/navbar_item.html
edc_navbar/templates/edc_navbar/select_language_item.html
edc_navbar/templatetags/__init__.py
edc_navbar/templatetags/edc_navbar_extras.py
edc_navbar/tests/__init__.py
edc_navbar/tests/admin.py
edc_navbar/tests/holidays.csv
edc_navbar/tests/models.py
edc_navbar/tests/test_settings.py
edc_navbar/tests/urls.py
edc_navbar/tests/etc/user-aes-local.key
edc_navbar/tests/etc/user-aes-restricted.key
edc_navbar/tests/etc/user-rsa-local-private.pem
edc_navbar/tests/etc/user-rsa-local-public.pem
edc_navbar/tests/etc/user-rsa-restricted-private.pem
edc_navbar/tests/etc/user-rsa-restricted-public.pem
edc_navbar/tests/etc/user-salt-local.key
edc_navbar/tests/etc/user-salt-restricted.key
edc_navbar/tests/tests/__init__.py
edc_navbar/tests/tests/test_auths.py
edc_navbar/tests/tests/test_navbar.py
edc_navbar-1.0.0.dist-info/AUTHORS
edc_navbar-1.0.0.dist-info/LICENSE
edc_navbar-1.0.0.dist-info/METADATA
edc_navbar-1.0.0.dist-info/WHEEL
edc_navbar-1.0.0.dist-info/top_level.txt
edc_navbar-1.0.0.dist-info/RECORD
